[
  {
    "q": "We're lost in the woods. Who makes the fire?",
    "A": "Me",
    "B": "We freeze together",
    "C": "Bear Grylls",
    "D": "You",
    "correct": "A"
  },
  {
    "q": "We have one battery left. Who gets it?",
    "A": "Split it somehow",
    "B": "The phone",
    "C": "Me",
    "D": "You",
    "correct": "D"
  },
  {
    "q": "Zombie apocalypse weapon of choice:",
    "A": "Baseball bat",
    "B": "Frying pan",
    "C": "Kitchen knife",
    "D": "Harsh language",
    "correct": "A"
  },
  {
    "q": "Our shelter priority is:",
    "A": "Find a cave",
    "B": "Build in trees",
    "C": "Find high ground",
    "D": "Stay near water",
    "correct": "C"
  },
  {
    "q": "Food runs out. What do we eat?",
    "A": "Hunt rabbits",
    "B": "Each other's cooking",
    "C": "Forage for berries",
    "D": "Fish in streams",
    "correct": "C"
  }
]